china_district/__init__.py
china_district/core.py
china_district-0.0.5.dist-info/LICENSE
china_district-0.0.5.dist-info/METADATA
china_district-0.0.5.dist-info/WHEEL
china_district-0.0.5.dist-info/top_level.txt
china_district-0.0.5.dist-info/RECORD
